mcp_debug/__init__.py
mcp_debug/__main__.py
mcp_debug-1.1.6.dist-info/METADATA
mcp_debug-1.1.6.dist-info/WHEEL
mcp_debug-1.1.6.dist-info/entry_points.txt
mcp_debug-1.1.6.dist-info/RECORD
