Metadata-Version: 2.4
Name: mcp-debug
Version: 1.1.6
Summary: A debugging and development tool for MCP servers with hot-swapping, session recording, and automated playback testing
Project-URL: Homepage, https://github.com/standardbeagle/mcp-debug
Project-URL: Repository, https://github.com/standardbeagle/mcp-debug
Project-URL: Issues, https://github.com/standardbeagle/mcp-debug/issues
Author: StandardBeagle
License-Expression: MIT
Keywords: debugging,development,mcp,model-context-protocol,proxy
Classifier: Development Status :: 4 - Beta
Classifier: Environment :: Console
Classifier: Intended Audience :: Developers
Classifier: License :: OSI Approved :: MIT License
Classifier: Operating System :: OS Independent
Classifier: Programming Language :: Python :: 3
Classifier: Programming Language :: Python :: 3.10
Classifier: Programming Language :: Python :: 3.11
Classifier: Programming Language :: Python :: 3.12
Classifier: Topic :: Software Development :: Debuggers
Classifier: Topic :: Software Development :: Testing
Requires-Python: >=3.10
